labo1/__init__.py
labo1/fit.py
labo1/round.py
labo1/tests/test_fit.py
labo1/tests/test_round.py
labo1-2.0.0.dist-info/LICENSE
labo1-2.0.0.dist-info/METADATA
labo1-2.0.0.dist-info/WHEEL
labo1-2.0.0.dist-info/top_level.txt
labo1-2.0.0.dist-info/RECORD
