Metadata-Version: 2.1
Name: labo1
Version: 2.0.0
Author-email: Mauro Silberberg <maurosilber@gmail.com>
License: MIT License
Project-URL: Homepage, https://github.com/maurosilber/labo1
Project-URL: Bug Tracker, https://github.com/maurosilber/labo1/issues
Classifier: Programming Language :: Python :: 3
Classifier: License :: OSI Approved :: MIT License
Classifier: Operating System :: OS Independent
Classifier: Intended Audience :: Science/Research
Classifier: Topic :: Scientific/Engineering
Requires-Python: >=3.8
License-File: LICENSE
Requires-Dist: numpy
Requires-Dist: scipy
Requires-Dist: matplotlib
